bio2bel_msig/__init__.py
bio2bel_msig/__main__.py
bio2bel_msig/cli.py
bio2bel_msig/constants.py
bio2bel_msig/manager.py
bio2bel_msig/models.py
bio2bel_msig/parser.py
bio2bel_msig/web.py
bio2bel_msig-0.2.0.dist-info/LICENSE
bio2bel_msig-0.2.0.dist-info/METADATA
bio2bel_msig-0.2.0.dist-info/WHEEL
bio2bel_msig-0.2.0.dist-info/entry_points.txt
bio2bel_msig-0.2.0.dist-info/top_level.txt
bio2bel_msig-0.2.0.dist-info/RECORD
