Metadata-Version: 2.1
Name: bio2bel-msig
Version: 0.2.0
Summary: A package for converting MSigDB gene sets into BEL
Home-page: https://github.com/bio2bel/msig
Author: Daniel Domingo-Fernández
Author-email: daniel.domingo.fernandez@scai.fraunhofer.de
Maintainer: Charles Tapley Hoyt
Maintainer-email: cthoyt@gmail.com
License: MIT
Download-URL: https://github.com/bio2bel/msig/releases
Project-URL: Bug Tracker, https://github.com/bio2bel/msig/issues
Project-URL: Source Code, https://github.com/bio2bel/msig
Keywords: Biological Expression Language,BEL,Systems Biology
Platform: UNKNOWN
Classifier: Development Status :: 4 - Beta
Classifier: Environment :: Console
Classifier: Intended Audience :: Developers
Classifier: Intended Audience :: Science/Research
Classifier: License :: OSI Approved :: MIT License
Classifier: Operating System :: OS Independent
Classifier: Programming Language :: Python
Classifier: Programming Language :: Python :: 3.8
Classifier: Programming Language :: Python :: 3.7
Classifier: Programming Language :: Python :: 3 :: Only
Classifier: Topic :: Scientific/Engineering :: Bio-Informatics
Requires-Python: >=3.7
Requires-Dist: pybel (<0.15.0,>=0.14.9)
Requires-Dist: click
Requires-Dist: bio2bel[web] (<0.4.0,>=0.3.8)
Requires-Dist: pyobo (>=0.2.2)
Requires-Dist: tqdm
Requires-Dist: sqlalchemy
Requires-Dist: requests
Requires-Dist: pandas
Provides-Extra: docs
Requires-Dist: sphinx ; extra == 'docs'
Requires-Dist: sphinx-rtd-theme ; extra == 'docs'
Requires-Dist: sphinx-click ; extra == 'docs'
Requires-Dist: sphinx-autodoc-typehints ; extra == 'docs'
